{
    "id": "943c723b-2837-4453-8513-1619ea37d517",
    "link": "https://www.rhs.org.uk/plants/10423/lolium-perenne/details",
    "tags": [
        "Grass Like"
    ],
    "names": {
        "other_common_names": [
            "English rye grass",
            "ever grass",
            "perennial rye grass",
            "ray",
            "ray grass",
            "red darnel",
            "rye grass",
            "white nonesuch"
        ],
        "synonyms": [
            "Lolium perenne var. tenue"
        ]
    },
    "size": {
        "ultimate_height": "0.5–1 metres",
        "time_to_ultimate_height": "5–10 years",
        "ultimate_spread": "Wider than 8 metres"
    },
    "growing_conditions": {
        "soil": [
            "Chalk",
            "Clay",
            "Loam",
            "Sand"
        ],
        "moisture": [
            "Moist but well–drained",
            "Well–drained"
        ],
        "ph": [
            "Acid",
            "Alkaline",
            "Neutral"
        ]
    },
    "colour_and_scent": {
        "spring": {
            "stem": [],
            "flower": [],
            "foliage": [
                "Green",
                "Grey",
                "Silver"
            ],
            "fruit": []
        },
        "summer": {
            "stem": [],
            "flower": [
                "Green",
                "Brown"
            ],
            "foliage": [
                "Green",
                "Grey",
                "Silver"
            ],
            "fruit": []
        },
        "autumn": {
            "stem": [],
            "flower": [],
            "foliage": [
                "Green",
                "Grey",
                "Silver"
            ],
            "fruit": []
        },
        "winter": {
            "stem": [],
            "flower": [],
            "foliage": [
                "Green",
                "Grey",
                "Silver"
            ],
            "fruit": []
        }
    },
    "position": {
        "sun_position": [
            "Full sun"
        ],
        "aspect_position": [
            "South–facing",
            "West–facing",
            "East–facing"
        ],
        "exposure": "Exposed or Sheltered",
        "hardiness": "H7"
    },
    "botanical_details": {
        "family": "Poaceae",
        "native_to_the_uk": "No",
        "foliage": "Evergreen",
        "habit": "Clump forming, Tufted",
        "name_status": "Correct"
    },
    "how_to_grow": {
        "cultivation": {
            "text": "Grow in any well-drained soil in full sun. Suited to lawns and turf and spread is indefinite so may be difficult to contain unless regularly maintained or used in a wild garden",
            "link_names": [],
            "related_links": {}
        },
        "propagation": {
            "text": "Propagate by seed in early spring or autumn, or by division from mid spring to early autumn",
            "link_names": [
                "Propagate by seed",
                "Division"
            ],
            "related_links": {
                "propagate_by_seed": "https://www.rhs.org.uk/propagation/sowing-seed-outdoors",
                "division": "https://www.rhs.org.uk/plants/types/perennials/dividing"
            }
        },
        "suggested_planting_locations_and_garden_types": {
            "text": [
                "Coastal",
                "Cottage and informal garden",
                "Wildlife gardens",
                "Wildflower meadow",
                "Garden edging",
                "Ground cover"
            ],
            "link_names": [],
            "related_links": {}
        },
        "pruning": {
            "text": "Cut down dead growth in autumn",
            "link_names": [],
            "related_links": {}
        },
        "pests": {
            "text": "May be susceptible to chafer grubs in lawns",
            "link_names": [
                "Chafer grubs"
            ],
            "related_links": {
                "chafer_grubs": "https://www.rhs.org.uk/biodiversity/chafer-grubs-in-garden-borders"
            }
        },
        "diseases": {
            "text": "May be susceptible to a rust",
            "link_names": [
                "A rust"
            ],
            "related_links": {
                "a_rust": "https://www.rhs.org.uk/disease/rust-diseases"
            }
        }
    },
    "pt_data": {
        "pt_link": "https://www.picturethisai.com/wiki/Lolium_perenne.html",
        "filename": "10423-lolium-perenne.json",
        "latin_name": "Lolium perenne",
        "common_names": [
            "Perennial ryegrass",
            "Common ray grass",
            "English ryegrass",
            "Winter ryegrass",
            "Ray grass"
        ],
        "synonyms": [
            "Lolium cechicum",
            "Lolium perenne var. stoloniferum",
            "Lolium halleri",
            "Lolium perenne var. scabriculme",
            "Lolium marschallii",
            "Lolium rigidum var. compressum",
            "Lolium perenne var. aristulatum",
            "Lolium perenne var. paniculatum",
            "Lolium vulgare",
            "Lolium montevidense",
            "Lolium rosetlanum",
            "Lolium perenne var. compositum",
            "Lolium felix",
            "Lolium perenne var. pacyi",
            "Lolium perenne var. vulgare",
            "Lolium perenne subsp. tenue",
            "Lolium pseudoitalicum",
            "Lolium strictum var. compressum",
            "Lolium perenne var. ramosum",
            "Lolium perenne var. orgiale",
            "Lolium annuum",
            "Lolium latum",
            "Hordeum compressum",
            "Lolium perenne var. purpurascens",
            "Lolium perenne var. brasilianum",
            "Lolium perenne f. microstachyum",
            "Lolium perenne var. compressum",
            "Lolium compressum",
            "Lolium tenue",
            "Lolium perenne var. monstrosum",
            "Lolium brasilianum",
            "Lolium perenne var. festuciforme",
            "Lolium perenne var. tenue",
            "Lolium perenne subsp. trabutii",
            "Lolium perenne var. viviparum",
            "Lolium perenne var. whitworthiense",
            "Lolium trabutii",
            "Lolium agreste",
            "Lolium repens",
            "Lolium perenne var. commune",
            "Lolium glumosum",
            "Lolium jechelianum",
            "Lolium perenne var. stickneiensis",
            "Lolium aechicum",
            "Festuca perennis",
            "Lolium perenne var. humile",
            "Lolium perenne subsp. stoloniferum",
            "Lolium canadense",
            "Lolium gmelinii",
            "Lolium perenne var. cristatum",
            "Lolium perenne",
            "Lolium cristatum",
            "Lolium perenne var. paleaceum"
        ],
        "ru_data": {
            "common_names": [
                "Плевел многолетний",
                "Пастбищный рейграс",
                "Английский райграс",
                "Райграс многолетний"
            ],
            "synonyms": [
                "Lolium cechicum",
                "Lolium perenne var. stoloniferum",
                "Lolium halleri",
                "Lolium perenne var. scabriculme",
                "Lolium marschallii",
                "Lolium rigidum var. compressum",
                "Lolium perenne var. aristulatum",
                "Lolium perenne var. paniculatum",
                "Lolium vulgare",
                "Lolium montevidense",
                "Lolium rosetlanum",
                "Lolium perenne var. compositum",
                "Lolium felix",
                "Lolium perenne var. pacyi",
                "Lolium perenne var. vulgare",
                "Lolium perenne subsp. tenue",
                "Lolium pseudoitalicum",
                "Lolium strictum var. compressum",
                "Lolium perenne var. ramosum",
                "Lolium perenne var. orgiale",
                "Lolium annuum",
                "Lolium latum",
                "Hordeum compressum",
                "Lolium perenne var. purpurascens",
                "Lolium perenne var. brasilianum",
                "Lolium perenne f. microstachyum",
                "Lolium perenne var. compressum",
                "Lolium compressum",
                "Lolium tenue",
                "Lolium perenne var. monstrosum",
                "Lolium brasilianum",
                "Lolium perenne var. festuciforme",
                "Lolium perenne var. tenue",
                "Lolium perenne subsp. trabutii",
                "Lolium perenne var. viviparum",
                "Lolium perenne var. whitworthiense",
                "Lolium trabutii",
                "Lolium agreste",
                "Lolium repens",
                "Lolium perenne var. commune",
                "Lolium glumosum",
                "Lolium jechelianum",
                "Lolium perenne var. stickneiensis",
                "Lolium aechicum",
                "Festuca perennis",
                "Lolium perenne var. humile",
                "Lolium perenne subsp. stoloniferum",
                "Lolium canadense",
                "Lolium gmelinii",
                "Lolium perenne var. cristatum",
                "Lolium perenne",
                "Lolium cristatum",
                "Lolium perenne var. paleaceum"
            ]
        },
        "rank": 2233,
        "items_data": {
            "water": "Twice per week",
            "sunlight": "Full sun",
            "planting_time": [
                "Spring",
                "Fall"
            ]
        },
        "class_data": {
            "phylum": "Vascular plants",
            "class": "Monocotyledons",
            "order": [
                "Grasses",
                "Sedges and allies"
            ],
            "family": "Grass",
            "genus": "Ryegrasses",
            "species": "Perennial ryegrass"
        },
        "toxic_data": [],
        "diseases_data": [
            "Scars",
            "Leaf tips withering",
            "Flower withering",
            "Fire ants"
        ]
    },
    "main_name_original": "Lolium perenne",
    "display_name": "Crappe",
    "clear_main_name": "Lolium perenne",
    "pt_search_main_name": "Lolium perenne"
}