{
    "id": "d70b0e7d-d6fa-4a03-89f8-e8dfc72afe96",
    "link": "https://www.rhs.org.uk/plants/108893/rhododendron-pachysanthum-crosswater/details",
    "main_name": "Rhododendron pachysanthum 'Crosswater'",
    "tags": [
        "Shrubs"
    ],
    "names": {},
    "size": {
        "ultimate_height": "1.5\u20132.5 metres",
        "time_to_ultimate_height": "10\u201320 years",
        "ultimate_spread": "1.5\u20132.5 metres"
    },
    "growing_conditions": {
        "soil": [
            "Clay",
            "Loam",
            "Sand"
        ],
        "moisture": [
            "Moist but well\u2013drained"
        ],
        "ph": [
            "Acid"
        ]
    },
    "colour_and_scent": {
        "spring": {
            "stem": [],
            "flower": [
                "Pink",
                "White"
            ],
            "foliage": [
                "Green",
                "Grey",
                "Silver"
            ],
            "fruit": []
        },
        "summer": {
            "stem": [],
            "flower": [],
            "foliage": [
                "Green",
                "Brown",
                "Grey"
            ],
            "fruit": []
        },
        "autumn": {
            "stem": [],
            "flower": [],
            "foliage": [
                "Green",
                "Grey",
                "Silver"
            ],
            "fruit": []
        },
        "winter": {
            "stem": [],
            "flower": [],
            "foliage": [
                "Green",
                "Grey",
                "Silver"
            ],
            "fruit": []
        }
    },
    "position": {
        "sun_position": [
            "Full shade",
            "Partial shade"
        ],
        "aspect_position": [
            "South\u2013facing",
            "East\u2013facing",
            "West\u2013facing"
        ],
        "exposure": "Sheltered",
        "hardiness": "H6"
    },
    "botanical_details": {
        "family": "Ericaceae",
        "native_to_the_uk": "No",
        "foliage": "Evergreen",
        "habit": "Bushy",
        "genus": "Rhododendron can be evergreen or deciduous shrubs or trees, with simple leaves, sometimes with a dense colourful indumentum of hairs on the lower side, and funnel-shaped, bell-shaped or tubular flowers that may be solitary or in short racemes",
        "name_status": "Accepted"
    },
    "how_to_grow": {
        "cultivation": "Grow in moist but well-drained, leafy, humus-rich, acid soil with shelter from strong winds. Will tolerate full sun but best in semi-shade; see rhododendron cultivation",
        "propagation": "Propagate by semi-ripe cuttings in late summer, layering in autumn or grafting in late summer or late winter",
        "suggested_planting_locations_and_garden_types": [
            "City and courtyard gardens",
            "Cottage and informal garden",
            "Flower borders and beds"
        ],
        "pruning": "Pruning group 1",
        "pests": "May be susceptible to vine weevil, rhododendron leafhopper, pieris lacebug, scale insects, caterpillars and aphids",
        "diseases": "May be susceptible to various rhododendron diseases including powdery mildews, rhododendron petal blight, rhododendron bud blast, silver leaf and honey fungus"
    }
}