{
    "id": "fc246b76-95d5-4f95-bc7d-6e413d5e4122",
    "link": "https://www.rhs.org.uk/plants/136891/matthiola-bicornis/details",
    "tags": [
        "Annual Biennial",
        "Synonym"
    ],
    "names": {
        "other_common_names": [
            "evening stock",
            "Grecian stock",
            "perfume plant",
            "night-scented violet [2]"
        ],
        "synonyms": [
            "Matthiola bicornis"
        ]
    },
    "size": {
        "ultimate_height": "0.1–0.5 metres",
        "time_to_ultimate_height": "1 year",
        "ultimate_spread": "0.1–0.5 metres"
    },
    "growing_conditions": {
        "soil": [
            "Chalk",
            "Loam",
            "Sand"
        ],
        "moisture": [
            "Moist but well–drained"
        ],
        "ph": [
            "Alkaline",
            "Neutral"
        ]
    },
    "colour_and_scent": {
        "fragrance": "Flower",
        "spring": {
            "stem": [],
            "flower": [],
            "foliage": [
                "Green",
                "Grey",
                "Silver"
            ],
            "fruit": []
        },
        "summer": {
            "stem": [],
            "flower": [
                "Pink",
                "Purple",
                "White"
            ],
            "foliage": [
                "Green",
                "Grey",
                "Silver"
            ],
            "fruit": []
        },
        "autumn": {
            "stem": [],
            "flower": [],
            "foliage": [],
            "fruit": []
        },
        "winter": {
            "stem": [],
            "flower": [],
            "foliage": [],
            "fruit": []
        }
    },
    "position": {
        "sun_position": [
            "Full sun"
        ],
        "aspect_position": [
            "South–facing",
            "West–facing"
        ],
        "exposure": "Sheltered",
        "hardiness": "H5"
    },
    "botanical_details": {
        "family": "Brassicaceae",
        "native_to_the_uk": "No",
        "foliage": "Deciduous",
        "habit": "Bushy",
        "genus": "Matthiola can be annuals, perennials or subshrubs, with simple or lobed leaves and dense terminal racemes or panicles of fragrant, 4-petalled flowers",
        "name_status": "Correct"
    },
    "how_to_grow": {
        "cultivation": {
            "text": "Grow in a sunny, sheltered bed where the soil is well-drained and neutral to slightly alkaline",
            "link_names": [],
            "related_links": {}
        },
        "propagation": {
            "text": "Propagate by seed sown in situ in spring, and repeated later for a succession of flowers",
            "link_names": [
                "Propagate by seed"
            ],
            "related_links": {
                "propagate_by_seed": "https://www.rhs.org.uk/propagation/sowing-seed-outdoors"
            }
        },
        "suggested_planting_locations_and_garden_types": {
            "text": [
                "Cottage and informal garden",
                "Flower borders and beds"
            ],
            "link_names": [],
            "related_links": {}
        },
        "pruning": {
            "text": "No pruning needed",
            "link_names": [],
            "related_links": {}
        },
        "pests": {
            "text": "May be susceptible to aphids, slugs and snails",
            "link_names": [
                "Aphids",
                "Slugs",
                "Snails"
            ],
            "related_links": {
                "aphids": "https://www.rhs.org.uk/biodiversity/aphids",
                "slugs": "https://www.rhs.org.uk/biodiversity/slugs",
                "snails": "https://www.rhs.org.uk/biodiversity/snails"
            }
        },
        "diseases": {
            "text": "Generally problem free",
            "link_names": [],
            "related_links": {}
        }
    },
    "main_name_original": "Matthiola bicornis",
    "display_name": "Night-scented stock",
    "clear_main_name": "Matthiola bicornis"
}