{
    "link": "https://www.rhs.org.uk/plants/138514/syringa-hyacinthiflora-maiden-s-blush/details",
    "main_name": "Syringa \u00d7 hyacinthiflora 'Maiden's Blush'",
    "tags": [
        "Shrubs"
    ],
    "names": {
        "synonyms": [
            "Syringa vulgaris 'Maiden's Blush'"
        ]
    },
    "size": {
        "ultimate_height": "2.5\u20134 metres",
        "time_to_ultimate_height": "2\u20135 years",
        "ultimate_spread": "2.5\u20134 metres"
    },
    "growing_conditions": {
        "soil": [
            "Chalk",
            "Clay",
            "Loam",
            "Sand"
        ],
        "moisture": [
            "Moist but well\u2013drained",
            "Well\u2013drained"
        ],
        "ph": [
            "Alkaline",
            "Neutral"
        ]
    },
    "colour_and_scent": {
        "fragrance": "Flower",
        "spring": {
            "stem": [],
            "flower": [
                "Pink"
            ],
            "foliage": [
                "Green"
            ],
            "fruit": []
        },
        "summer": {
            "stem": [],
            "flower": [],
            "foliage": [
                "Green"
            ],
            "fruit": []
        },
        "autumn": {
            "stem": [],
            "flower": [],
            "foliage": [
                "Green"
            ],
            "fruit": []
        },
        "winter": {
            "stem": [],
            "flower": [],
            "foliage": [],
            "fruit": []
        }
    },
    "position": {
        "sun_position": [
            "Full sun"
        ],
        "aspect_position": [
            "South\u2013facing",
            "West\u2013facing"
        ],
        "exposure": "Exposed or Sheltered",
        "hardiness": "H6"
    },
    "botanical_details": {
        "family": "Oleaceae",
        "native_to_the_uk": "No",
        "foliage": "Deciduous",
        "habit": "Bushy",
        "genus": "Syringa can be deciduous shrubs or trees, with simple, entire or rarely pinnate leaves and conical panicles of small, very fragrant, 4-lobed tubular flowers in late spring or early summer",
        "name_status": "Accepted"
    },
    "how_to_grow": {
        "cultivation": "Grow in well-drained, fertile, humus-rich alkaline to neutral soils. Mulch regularly",
        "propagation": "Propagate by softwood cuttings or layering in early summer, chip budding in summer or grafting in winter",
        "suggested_planting_locations_and_garden_types": [
            "City and courtyard gardens",
            "Coastal",
            "Cottage and informal garden",
            "Low Maintenance",
            "Flower borders and beds",
            "Wall side borders"
        ],
        "pruning": "Pruning group 1 or 2, after flowering",
        "pests": "May be susceptible to lilac leaf-mining moth, thrips and willow scale insects",
        "diseases": "May be susceptible to lilac blight, honey fungus and bacterial canker"
    }
}