{
    "id": "aaa1334e-bbc9-493d-8b25-c939955404eb",
    "link": "https://www.rhs.org.uk/plants/156937/lobelia-weslowei-pbr/details",
    "main_name": "Lobelia 'Weslowei'PBR",
    "tags": [
        "Annual Biennial",
        "Bedding",
        "Synonym"
    ],
    "names": {
        "synonyms": [
            "Lobelia 'Weslowei'PBR"
        ]
    },
    "size": {
        "ultimate_height": "0.1–0.5 metres",
        "time_to_ultimate_height": "1 year",
        "ultimate_spread": "0.1–0.5 metres"
    },
    "growing_conditions": {
        "soil": [
            "Loam",
            "Sand"
        ],
        "moisture": [
            "Moist but well–drained",
            "Well–drained"
        ],
        "ph": [
            "Acid",
            "Alkaline",
            "Neutral"
        ]
    },
    "colour_and_scent": {
        "spring": {
            "stem": [],
            "flower": [
                "White"
            ],
            "foliage": [
                "Green"
            ],
            "fruit": []
        },
        "summer": {
            "stem": [],
            "flower": [
                "White"
            ],
            "foliage": [
                "Green"
            ],
            "fruit": []
        },
        "autumn": {
            "stem": [],
            "flower": [
                "White"
            ],
            "foliage": [
                "Green"
            ],
            "fruit": []
        },
        "winter": {
            "stem": [],
            "flower": [],
            "foliage": [],
            "fruit": []
        }
    },
    "position": {
        "sun_position": [
            "Full sun",
            "Partial shade"
        ],
        "aspect_position": [
            "North–facing",
            "East–facing",
            "South–facing",
            "West–facing"
        ],
        "exposure": "Sheltered",
        "hardiness": "H2"
    },
    "botanical_details": {
        "family": "Campanulaceae",
        "native_to_the_uk": "No",
        "foliage": "Deciduous",
        "habit": "Trailing",
        "genus": "Lobelia can be annuals, perennials or shrubs, with simple leaves and showy 2-lipped flowers that may be solitary or in racemes or panicles",
        "name_status": "Trade"
    },
    "how_to_grow": {
        "cultivation": {
            "text": "Best in moist but well-drained soil, in light shade. Ideal for containers",
            "link_names": [
                "Containers"
            ],
            "related_links": {
                "containers": "https://www.rhs.org.uk/container-gardening/maintenance"
            }
        },
        "propagation": {
            "text": "Propagate by softwood cuttings",
            "link_names": [
                "Softwood"
            ],
            "related_links": {
                "softwood": "https://www.rhs.org.uk/propagation/softwood-cuttings"
            }
        },
        "suggested_planting_locations_and_garden_types": {
            "text": [
                "City and courtyard gardens",
                "Cottage and informal garden",
                "Patio and container plants"
            ],
            "link_names": [],
            "related_links": {}
        },
        "pruning": {
            "text": "No pruning required",
            "link_names": [],
            "related_links": {}
        },
        "pests": {
            "text": "Slugs and greenfly may be a problem",
            "link_names": [
                "Slugs"
            ],
            "related_links": {
                "slugs": "https://www.rhs.org.uk/biodiversity/slugs"
            }
        },
        "diseases": {
            "text": "Generally disease-free",
            "link_names": [],
            "related_links": {}
        }
    },
    "main_name_original": "Lobelia 'Weslowei'PBR",
    "display_name": "Lobelia [white star]"
}