{
    "id": "92735d0d-5a18-4b45-a3bc-82c44693cec2",
    "link": "https://www.rhs.org.uk/plants/161481/tamarix-chinensis/details",
    "main_name": "Tamarix chinensis",
    "tags": [
        "Shrubs",
        "Trees"
    ],
    "names": {
        "other_common_names": [
            "Chinese tree"
        ],
        "synonyms": [
            "Tamarix plumosa",
            "Tamarix juniperina",
            "Tamarix japonica"
        ]
    },
    "size": {
        "ultimate_height": "4–8 metres",
        "time_to_ultimate_height": "10–20 years",
        "ultimate_spread": "2.5–4 metres"
    },
    "growing_conditions": {
        "soil": [
            "Clay",
            "Loam",
            "Sand"
        ],
        "moisture": [
            "Moist but well–drained",
            "Well–drained"
        ],
        "ph": [
            "Acid",
            "Neutral"
        ]
    },
    "colour_and_scent": {
        "spring": {
            "stem": [],
            "flower": [
                "Pink"
            ],
            "foliage": [
                "Green",
                "Grey",
                "Silver"
            ],
            "fruit": []
        },
        "summer": {
            "stem": [],
            "flower": [],
            "foliage": [
                "Green",
                "Grey",
                "Silver"
            ],
            "fruit": []
        },
        "autumn": {
            "stem": [],
            "flower": [],
            "foliage": [
                "Green",
                "Grey",
                "Silver"
            ],
            "fruit": []
        },
        "winter": {
            "stem": [],
            "flower": [],
            "foliage": [],
            "fruit": []
        }
    },
    "position": {
        "sun_position": [
            "Full sun"
        ],
        "aspect_position": [
            "East–facing",
            "North–facing",
            "South–facing",
            "West–facing"
        ],
        "exposure": "Exposed or Sheltered",
        "hardiness": "H5"
    },
    "botanical_details": {
        "family": "Tamaricaceae",
        "native_to_the_uk": "No",
        "foliage": "Deciduous",
        "habit": "Bushy",
        "genus": "Tamarix are deciduous shrubs or small trees of feathery effect, with minute leaves and racemes of very small pink or white flowers in spring, summer or early autumn",
        "name_status": "Correct",
        "plant_range": "China"
    },
    "how_to_grow": {
        "cultivation": "Grows well in most soils but dislikes shallow chalky soil. Requires full sun and a well-drained sandy soil in coastal plantings but it requires shelter from cold drying winds when planted inland",
        "propagation": "Propagate by semi-hardwood cuttings in summer or hardwood cuttings in winter. Propagate by seed sown, when ripe, in containers in a cold-frame",
        "suggested_planting_locations_and_garden_types": [
            "Coastal",
            "Cottage and informal garden",
            "Low Maintenance"
        ],
        "pruning": "Pruning group 2",
        "pests": "Generally pest-free",
        "diseases": "Generally disease-free"
    },
    "pt_data": {
        "pt_link": "https://www.picturethisai.com/wiki/Tamarix_chinensis.html",
        "filename": "161481-tamarix-chinensis.json",
        "latin_name": "Tamarix chinensis",
        "common_names": [
            "Five-stamen tamarisk",
            "China tamarisk",
            "Chinese tamarisk",
            "Chinese saltcedar",
            "Saltcedar"
        ],
        "synonyms": [
            "Tamarix tenuissima",
            "Tamarix plumosa",
            "Tamarix gallica var. chinensis",
            "Tamarix gallica",
            "Tamarix japonica",
            "Tamarix juniperina",
            "Tamarix caspica",
            "Tamarix elegans",
            "Tamarix chinensis"
        ],
        "ru_data": {
            "common_names": [
                "Гребенщик китайский"
            ],
            "synonyms": [
                "Tamarix tenuissima",
                "Tamarix plumosa",
                "Tamarix gallica var. chinensis",
                "Tamarix gallica",
                "Tamarix japonica",
                "Tamarix juniperina",
                "Tamarix caspica",
                "Tamarix elegans",
                "Tamarix chinensis"
            ]
        },
        "rank": 6627,
        "items_data": {
            "sunlight": "Full sun"
        },
        "class_data": {
            "phylum": "Vascular plants",
            "class": "Dicotyledons",
            "order": [
                "Pinks",
                "Cacti",
                "Allies"
            ],
            "family": "Tamarisk",
            "genus": "Tamarisks",
            "species": "Five-stamen tamarisk"
        },
        "toxic_data": [],
        "diseases_data": []
    }
}