{
    "latin_name": "Carpinus turczaninowii",
    "main_common_name": {
        "en": "Carpinus turczaninowii",
        "ru": "Carpinus turczaninowii"
    },
    "common_names": {
        "en": [
            "Carpinus turczaninowii"
        ],
        "ru": [
            "Carpinus turczaninowii"
        ]
    },
    "synonyms": [
        "Carpinus stipulata"
    ],
    "tags": [
        "Trees"
    ],
    "genus_description": "Carpinus are deciduous shrubs and trees with attractive foliage and hop-like fruit clusters in late summer and autumn",
    "rank": 999999,
    "size": {
        "ultimate_height": "8–12 metres",
        "time_to_ultimate_height": "20–50 years",
        "ultimate_spread": "4–8 metres"
    },
    "soil": {
        "water": "Every 1-2 weeks",
        "type": [
            "Chalk",
            "Clay",
            "Loam",
            "Sand"
        ],
        "moisture": [
            "Moist but well–drained",
            "Well–drained"
        ],
        "ph": [
            "Acid",
            "Alkaline",
            "Neutral"
        ]
    },
    "position": {
        "sunlight": [
            "Full sun",
            "Partial shade"
        ],
        "side": [
            "North–facing",
            "South–facing",
            "West–facing",
            "East–facing"
        ],
        "exposure": "Exposed or Sheltered",
        "hardiness_zone": "H6"
    },
    "events": {
        "harvest": [],
        "planting": []
    },
    "colour_and_scent": {
        "fragrance": null,
        "spring": {
            "stem": [],
            "flower": [
                "Green",
                "Yellow"
            ],
            "foliage": [
                "Red",
                "Green"
            ],
            "fruit": []
        },
        "summer": {
            "stem": [],
            "flower": [],
            "foliage": [
                "Green"
            ],
            "fruit": []
        },
        "autumn": {
            "stem": [],
            "flower": [],
            "foliage": [
                "Orange"
            ],
            "fruit": [
                "Green"
            ]
        },
        "winter": {
            "stem": [],
            "flower": [],
            "foliage": [],
            "fruit": []
        }
    },
    "toxicity": [],
    "how_to_grow": {
        "cultivation": "Grows well in most moderately fertile, well-drained soils. Excellent as a smaller woodland tree or in a parkland setting",
        "propagation": [
            "Propagate by seed",
            "Softwood",
            "Grafting"
        ],
        "suggested_panting_places": [
            "Architectural",
            "Low Maintenance",
            "Banks and slopes",
            "Hedging and screens"
        ],
        "pruning": [
            "Pruning group 1"
        ]
    },
    "diseases_and_pests": [],
    "scientific_classification": {
        "family": "Birch",
        "phylum": "Vascular plants",
        "classify": "Dicotyledons",
        "order": [
            "Beeches",
            "Walnuts",
            "And allied trees"
        ],
        "genus": "Hornbeams",
        "species": "Carpinus turczaninowii"
    },
    "botanical_details": {
        "plant_range": "N China to Japan",
        "foliage": "Deciduous",
        "habit": "Bushy"
    }
}