{
    "id": "ae949c74-7023-4792-9a4c-7fc832d20568",
    "link": "https://www.rhs.org.uk/plants/3370/centaurea-scabiosa/details",
    "tags": [
        "Herbaceous Perennial"
    ],
    "names": {
        "other_common_names": [
            "black top"
        ],
        "synonyms": [
            "Centaurea scabiosa var. petrophila"
        ]
    },
    "size": {
        "ultimate_height": "0.5–1 metres",
        "time_to_ultimate_height": "2–5 years",
        "ultimate_spread": "0.1–0.5 metres"
    },
    "growing_conditions": {
        "soil": [
            "Chalk",
            "Clay",
            "Loam",
            "Sand"
        ],
        "moisture": [
            "Moist but well–drained"
        ],
        "ph": [
            "Acid",
            "Alkaline",
            "Neutral"
        ]
    },
    "colour_and_scent": {
        "spring": {
            "stem": [],
            "flower": [],
            "foliage": [
                "Green"
            ],
            "fruit": []
        },
        "summer": {
            "stem": [],
            "flower": [
                "Purple",
                "Red"
            ],
            "foliage": [
                "Green"
            ],
            "fruit": []
        },
        "autumn": {
            "stem": [],
            "flower": [],
            "foliage": [
                "Green"
            ],
            "fruit": []
        },
        "winter": {
            "stem": [],
            "flower": [],
            "foliage": [],
            "fruit": []
        }
    },
    "position": {
        "sun_position": [
            "Full sun",
            "Partial shade"
        ],
        "aspect_position": [
            "West–facing",
            "South–facing",
            "North–facing",
            "East–facing"
        ],
        "exposure": "Exposed or Sheltered",
        "hardiness": "H6"
    },
    "botanical_details": {
        "family": "Asteraceae",
        "native_to_the_uk": "Yes",
        "foliage": "Deciduous",
        "habit": "Clump forming",
        "genus": "Centaurea may be annuals, perennials or subshrubs, with simple or pinnately lobed leaves and showy thistle-like flowers-heads, often with enlarged outer florets",
        "name_status": "Correct",
        "plant_range": "Europe"
    },
    "how_to_grow": {
        "cultivation": {
            "text": "Prefers a well-drained fertile soil in a sunny position. Tolerant of dry, alkaline soils and established plants are tolerant of considerable neglect. Self-seeds readily and can become invasive",
            "link_names": [],
            "related_links": {}
        },
        "propagation": {
            "text": "Propagate by seed",
            "link_names": [
                "Propagate by seed"
            ],
            "related_links": {
                "propagate_by_seed": "https://www.rhs.org.uk/propagation/sowing-seed-outdoors"
            }
        },
        "suggested_planting_locations_and_garden_types": {
            "text": [
                "Wildlife gardens",
                "Wildflower meadow",
                "Low Maintenance"
            ],
            "link_names": [],
            "related_links": {}
        },
        "pruning": {
            "text": "No pruning required",
            "link_names": [],
            "related_links": {}
        },
        "pests": {
            "text": "Generally pest-free. Resistant to browsing by deer",
            "link_names": [
                "Deer"
            ],
            "related_links": {
                "deer": "https://www.rhs.org.uk/biodiversity/deer"
            }
        },
        "diseases": {
            "text": "May be affected by powdery mildews",
            "link_names": [
                "Powdery mildews"
            ],
            "related_links": {
                "powdery_mildews": "https://www.rhs.org.uk/disease/powdery-mildews"
            }
        }
    },
    "pt_data": {
        "pt_link": "https://www.picturethisai.com/wiki/Centaurea_scabiosa.html",
        "filename": "3370-centaurea-scabiosa.json",
        "latin_name": "Centaurea scabiosa",
        "common_names": [
            "Greater knapweed",
            "Scabious star thistle",
            "Austrian knapweed",
            "Leathery knapweed"
        ],
        "synonyms": [
            "Centaurea scabiosa"
        ],
        "ru_data": {
            "common_names": [
                "Василёк шероховатый",
                "Василёк скабиозовый",
                "Василёк шершавый",
                "Василёк скабиозный",
                "Большеголовник",
                "Шалабольник"
            ],
            "synonyms": [
                "Centaurea scabiosa"
            ]
        },
        "rank": 3222,
        "items_data": {
            "sunlight": "Full sun"
        },
        "class_data": {
            "phylum": "Vascular plants",
            "class": "Dicotyledons",
            "order": "Asters bellflowers fanflowers and allies",
            "family": "Daisy",
            "genus": "Centaury",
            "species": "Greater knapweed"
        },
        "toxic_data": [],
        "diseases_data": []
    },
    "main_name_original": "Centaurea scabiosa",
    "display_name": "Greater knapweed",
    "clear_main_name": "Centaurea scabiosa",
    "pt_search_main_name": "Centaurea scabiosa"
}