{
    "link": "https://www.rhs.org.uk/plants/360353/stokesia-laevis-blue-frills/details",
    "main_name": "Stokesia laevis 'Blue Frills'",
    "tags": [
        "Herbaceous Perennial",
        "Synonym"
    ],
    "names": {
        "synonyms": [
            "Stokesia laevis 'Synstokhar'",
            "Stokesia laevis 'Blue Frills'"
        ]
    },
    "size": {
        "ultimate_height": "0.5\u20131 metres",
        "time_to_ultimate_height": "2\u20135 years",
        "ultimate_spread": "0.5\u20131 metres"
    },
    "growing_conditions": {
        "soil": [
            "Chalk",
            "Loam",
            "Sand"
        ],
        "moisture": [
            "Moist but well\u2013drained",
            "Well\u2013drained"
        ],
        "ph": [
            "Acid",
            "Alkaline",
            "Neutral"
        ]
    },
    "colour_and_scent": {
        "spring": {
            "stem": [],
            "flower": [],
            "foliage": [],
            "fruit": []
        },
        "summer": {
            "stem": [],
            "flower": [
                "Blue"
            ],
            "foliage": [
                "Green"
            ],
            "fruit": []
        },
        "autumn": {
            "stem": [],
            "flower": [
                "Blue"
            ],
            "foliage": [
                "Green"
            ],
            "fruit": []
        },
        "winter": {
            "stem": [],
            "flower": [],
            "foliage": [
                "Green"
            ],
            "fruit": []
        }
    },
    "position": {
        "sun_position": [
            "Full sun"
        ],
        "aspect_position": [
            "East\u2013facing",
            "South\u2013facing",
            "West\u2013facing"
        ],
        "exposure": "Sheltered",
        "hardiness": "H4"
    },
    "botanical_details": {
        "family": "Asteraceae",
        "native_to_the_uk": "No",
        "foliage": "Evergreen",
        "habit": "Clump forming",
        "genus": "Stokesia are perennials producing evergreen, basal rosettes. The colourful, cornflower-like flowers are long lasting and good for cutting",
        "name_status": "Trade"
    },
    "how_to_grow": {
        "cultivation": "Plant in light well drained soil in sunor light shade does best in acidic soil.",
        "propagation": "Propagate by division in spring or root cuttings in winter",
        "suggested_planting_locations_and_garden_types": [
            "City and courtyard gardens",
            "Cottage and informal garden",
            "Flower borders and beds"
        ],
        "pruning": "Deadhead to prolong flowering. Tidy foliage in spring when new growth appears.",
        "pests": "Generally pest-free",
        "diseases": "Generally disease-free"
    }
}