{
    "latin_name": "Echinocereus reichenbachii",
    "main_common_name": {
        "en": "Lace hedgehog cactus",
        "ru": "Эхиноцереус райхенбаха"
    },
    "common_names": {
        "en": [
            "Purple candle cactus",
            "Fitch's hedgehog cactus",
            "Purple candle",
            "Lace cactus",
            "Cob cactus",
            "Bailey's hedgehog cactus",
            "Lace hedgehog",
            "Lace cactus",
            "Hedgehog cactus",
            "Merry widow cactus",
            "Lace hedgehog cactus"
        ],
        "ru": [
            "Эхиноцереус райхенбаха"
        ]
    },
    "synonyms": [
        "Echinocereus reichenbachii subsp. armatus",
        "Echinocereus reichenbachii var. albispinus",
        "Echinocereus purpureus",
        "Echinocereus reichenbachii subsp. baileyi",
        "Echinocereus albispinus",
        "Echinocereus caespitosus var. minor",
        "Echinocereus baileyi",
        "Echinocereus melanocentrus",
        "Echinocereus caespitosus var. purpureus",
        "Echinocereus reichenbachii subsp. reichenbachii",
        "Echinocereus caespitosus var. perbellus",
        "Echinocereus caespitosus",
        "Echinocereus reichenbachii subsp. perbellus",
        "Echinocereus reichenbachii subsp. fitchii",
        "Echinocereus perbellus",
        "Echinocereus fitchii",
        "Echinocereus reichenbachii subsp. burrensis",
        "Echinocereus reichenbachii var. albertii",
        "Cereus pectinatus var. armatus",
        "Echinocereus baileyi var. albispinus",
        "Echinocereus reichenbachii var. fitchii",
        "Echinocereus reichenbachii"
    ],
    "tags": [
        "Cactus Succulent",
        "Conservatory Greenhouse"
    ],
    "genus_description": "Echinocereus can have deeply ribbed cylindrical or globose stems, sometimes forming clumps, and large funnel-shaped flowers",
    "rank": 5045,
    "size": {
        "ultimate_height": "0.1–0.5 metres",
        "time_to_ultimate_height": "10–20 years",
        "ultimate_spread": "0.1–0.5 metres"
    },
    "soil": {
        "water": "Every 3 weeks",
        "type": [
            "Loam",
            "Sand"
        ],
        "moisture": [
            "Well–drained"
        ],
        "ph": [
            "Acid",
            "Alkaline",
            "Neutral"
        ]
    },
    "position": {
        "sunlight": [
            "Full sun"
        ],
        "side": [
            "South–facing",
            "West–facing"
        ],
        "exposure": "Sheltered",
        "hardiness_zone": "H2"
    },
    "events": {
        "harvest": [],
        "planting": []
    },
    "colour_and_scent": {
        "fragrance": null,
        "spring": {
            "stem": [],
            "flower": [
                "Purple"
            ],
            "foliage": [],
            "fruit": []
        },
        "summer": {
            "stem": [],
            "flower": [
                "Purple"
            ],
            "foliage": [],
            "fruit": []
        },
        "autumn": {
            "stem": [],
            "flower": [],
            "foliage": [],
            "fruit": []
        },
        "winter": {
            "stem": [],
            "flower": [],
            "foliage": [],
            "fruit": []
        }
    },
    "toxicity": [],
    "how_to_grow": {
        "cultivation": "Grow under glass in a loam-based potting compost with added extra grit. Water moderately when in growth, not at all when dormant. Apply a balanced liquid fertiliser 2 or 3 times in the growing season",
        "propagation": [
            "Propagate by seed"
        ],
        "suggested_panting_places": [],
        "pruning": []
    },
    "diseases_and_pests": [
        "Mealybugs",
        "Fruit deformity",
        "Scars",
        "Stem rot"
    ],
    "scientific_classification": {
        "family": "Cactuses",
        "phylum": "Vascular plants",
        "classify": "Dicotyledons",
        "order": [
            "Pinks",
            "Cacti",
            "And allies"
        ],
        "genus": "Hedgehog cactus",
        "species": "Lace Hedgehog Cactus"
    },
    "botanical_details": {
        "plant_range": "NE Mexico, SW USA",
        "foliage": "Evergreen",
        "habit": "Columnar upright"
    }
}