{
    "id": "baf06871-07fb-414f-a730-97a0da1855c8",
    "link": "https://www.rhs.org.uk/plants/95075/agave-americana/details",
    "main_name": "Agave americana",
    "tags": [
        "Cactus Succulent"
    ],
    "names": {
        "other_common_names": [
            "American aloe",
            "maguey",
            "Mexican soap plant"
        ],
        "synonyms": [
            "Agave gracilispina"
        ]
    },
    "size": {
        "ultimate_height": "1–1.5 metres",
        "time_to_ultimate_height": "10–20 years",
        "ultimate_spread": "1–1.5 metres"
    },
    "growing_conditions": {
        "soil": [
            "Loam",
            "Sand"
        ],
        "moisture": [
            "Well–drained"
        ],
        "ph": [
            "Acid",
            "Neutral"
        ]
    },
    "colour_and_scent": {
        "spring": {
            "stem": [],
            "flower": [],
            "foliage": [
                "Green",
                "Grey",
                "Silver"
            ],
            "fruit": []
        },
        "summer": {
            "stem": [],
            "flower": [
                "Green",
                "Yellow"
            ],
            "foliage": [
                "Green",
                "Grey",
                "Silver"
            ],
            "fruit": []
        },
        "autumn": {
            "stem": [],
            "flower": [],
            "foliage": [
                "Green",
                "Grey",
                "Silver"
            ],
            "fruit": []
        },
        "winter": {
            "stem": [],
            "flower": [],
            "foliage": [
                "Green",
                "Grey",
                "Silver"
            ],
            "fruit": []
        }
    },
    "position": {
        "sun_position": [
            "Full sun"
        ],
        "aspect_position": [
            "East–facing",
            "South–facing"
        ],
        "exposure": "Sheltered",
        "hardiness": "H2"
    },
    "botanical_details": {
        "family": "Asparagaceae",
        "native_to_the_uk": "No",
        "foliage": "Evergreen",
        "habit": "Clump forming",
        "genus": "Agave can be perennial or monocarpic succulents, forming rosettes of usually rigid, fleshy, spiny-edged leaves, with funnel-shaped flowers in racemes or panicles often much taller than the rosettes",
        "name_status": "Correct",
        "plant_range": "S USA to Mexico"
    },
    "how_to_grow": {
        "cultivation": "Grow under glass in a standard cactus compost, in bright, filtered light. When in growth water moderately and feed every two or three weeks with a balanced liquid feed. Keep almost dry in the winter",
        "propagation": "Propagate by offsets taken in spring or autumn",
        "suggested_planting_locations_and_garden_types": [
            "Architectural",
            "City and courtyard gardens",
            "Patio and container plants",
            "Mediterranean climate plants",
            "Coastal"
        ],
        "pruning": "No pruning required",
        "pests": "May be attacked by scale insects",
        "diseases": "Generally disease free"
    },
    "pt_data": {
        "pt_link": "https://www.picturethisai.com/wiki/Agave_americana.html",
        "filename": "95075-agave-americana.json",
        "latin_name": "Agave americana",
        "common_names": [
            "Century plant",
            "American agave",
            "American aloe",
            "Flowering aloe",
            "Sentry plant",
            "Maguey"
        ],
        "synonyms": [
            "Aloe americana",
            "Agave spectabilis",
            "Agave americana"
        ],
        "ru_data": {
            "common_names": [
                "Ага́ва америка́нская"
            ],
            "synonyms": [
                "Aloe americana",
                "Agave spectabilis",
                "Agave americana"
            ]
        },
        "rank": 1293,
        "items_data": {
            "water": "Every 3 weeks",
            "sunlight": "Full sun",
            "hardiness_zones": "5 - 9",
            "planting_time": [
                "Spring",
                "Fall"
            ]
        },
        "class_data": {
            "phylum": "Vascular plants",
            "class": "Monocotyledons",
            "order": "Asparagus and allies",
            "family": "Asparagus",
            "genus": "Agaves",
            "species": "Century plant"
        },
        "toxic_data": [
            ""
        ],
        "diseases_data": [
            "Flower withering",
            "Aged yellow and dry",
            "Scars",
            "Plant dried up",
            "Low light",
            "Brown spot"
        ]
    }
}